uploadassist/__init__.py
uploadassist/cli.py
uploadassist/deps.py
uploadassist/latexmk.py
uploadassist/utils.py
uploadassist-0.0.1.dev1.dist-info/licenses/LICENSE
uploadassist-0.0.1.dev1.dist-info/METADATA
uploadassist-0.0.1.dev1.dist-info/WHEEL
uploadassist-0.0.1.dev1.dist-info/entry_points.txt
uploadassist-0.0.1.dev1.dist-info/top_level.txt
uploadassist-0.0.1.dev1.dist-info/RECORD
