Metadata-Version: 2.4
Name: uploadassist
Version: 0.0.1.dev1
Summary: A tool to package LaTeX sources for journal submission, forked from arxiv-collector. Adds LuaTeX/XeLaTeX support and a flatten option.
Author-email: Casper van Elteren <caspervanelteren@gmail.com>
License: BSD 3-Clause License
Project-URL: Homepage, https://github.com/cvanelteren/uploadassist
Project-URL: Repository, https://github.com/cvanelteren/uploadassist
Project-URL: Issues, https://github.com/cvanelteren/uploadassist/issues
Keywords: latex,submission,arxiv,journal,packaging,XeLaTeX,LuaTeX
Requires-Python: >=3.7
License-File: LICENSE
Dynamic: license-file
